<images>
	<image name='bg_rock1.jpg' new-name='bg_rock1.jpg'/>
	<image name='bg_rock.jpg' new-name='bg_rock.jpg'/>
	<image name='sm_rck4.jpg' new-name='sm_rck4.jpg'/>
	<image name='bg_rock4.jpg' new-name='bg_rock4.jpg'/>
	<image name='sm_rock.jpg' new-name='sm_rock.jpg'/>
	<image name='rise_u2.jpg' new-name='rise_u2.jpg'/>
	<image name='sm_rck1.jpg' new-name='sm_rck1.jpg'/>
	<image name='sm_rck3.jpg' new-name='sm_rck3.jpg'/>
	<image name='rise_u3.jpg' new-name='rise_u3.jpg'/>
	<image name='corn_b.jpg' new-name='corn_b.jpg'/>
	<image name='corn1.jpg' new-name='corn1.jpg'/>
	<image name='corn4.jpg' new-name='corn4.jpg'/>
	<image name='rise_u1.jpg' new-name='rise_u1.jpg'/>
	<image name='up_rock1.jpg' new-name='up_rock1.jpg'/>
	<image name='rockgras.jpg' new-name='rockgras.jpg'/>
	<image name='corn3.jpg' new-name='corn3.jpg'/>
	<image name='rise_r1.jpg' new-name='rise_r1.jpg'/>
	<image name='bg_rock3.jpg' new-name='bg_rock3.jpg'/>
	<image name='sm_rck2.jpg' new-name='sm_rck2.jpg'/>
	<image name='bg_rock2.jpg' new-name='bg_rock2.jpg'/>
	<image name='corn2.jpg' new-name='corn2.jpg'/>
</images>